djhtmx/__init__.py
djhtmx/apps.py
djhtmx/command_queue.py
djhtmx/commands.py
djhtmx/component.py
djhtmx/consumer.py
djhtmx/context.py
djhtmx/exceptions.py
djhtmx/global_events.py
djhtmx/introspection.py
djhtmx/json.py
djhtmx/middleware.py
djhtmx/query.py
djhtmx/repo.py
djhtmx/settings.py
djhtmx/testing.py
djhtmx/tracing.py
djhtmx/urls.py
djhtmx/utils.py
djhtmx/management/commands/htmx.py
djhtmx/static/htmx/django.js
djhtmx/static/htmx/2.0.4/htmx.amd.js
djhtmx/static/htmx/2.0.4/htmx.cjs.js
djhtmx/static/htmx/2.0.4/htmx.esm.d.ts
djhtmx/static/htmx/2.0.4/htmx.esm.js
djhtmx/static/htmx/2.0.4/htmx.js
djhtmx/static/htmx/2.0.4/htmx.min.js
djhtmx/static/htmx/2.0.4/ext/idiomorph-ext.min.js
djhtmx/static/htmx/2.0.4/ext/ws.js
djhtmx/templates/htmx/headers.html
djhtmx/templates/htmx/lazy.html
djhtmx/templatetags/__init__.py
djhtmx/templatetags/htmx.py
djhtmx-1.3.4.dist-info/METADATA
djhtmx-1.3.4.dist-info/WHEEL
djhtmx-1.3.4.dist-info/licenses/LICENSE
djhtmx-1.3.4.dist-info/RECORD
