Metadata-Version: 2.4
Name: djhtmx
Version: 1.3.4
Summary: Interactive UI Components for Django using HTMX
Project-URL: Homepage, https://github.com/edelvalle/djhtmx
Project-URL: Documentation, https://github.com/edelvalle/djhtmx#readme
Project-URL: Repository, https://github.com/edelvalle/djhtmx.git
Project-URL: Issues, https://github.com/edelvalle/djhtmx/issues
Project-URL: Changelog, https://github.com/edelvalle/djhtmx/blob/master/CHANGELOG.md
Author-email: Eddy Ernesto del Valle Pino <eddy@edelvalle.me>
License-Expression: MIT
License-File: LICENSE
Keywords: django,htmx,liveview,reactive,real-time,spa,websockets
Classifier: Development Status :: 5 - Production/Stable
Classifier: Environment :: Web Environment
Classifier: Framework :: Django
Classifier: Framework :: Django :: 4.1
Classifier: Framework :: Django :: 4.2
Classifier: Framework :: Django :: 5.0
Classifier: Framework :: Django :: 5.1
Classifier: Intended Audience :: Developers
Classifier: License :: OSI Approved :: MIT License
Classifier: Operating System :: OS Independent
Classifier: Programming Language :: Python
Classifier: Programming Language :: Python :: 3
Classifier: Programming Language :: Python :: 3.11
Classifier: Programming Language :: Python :: 3.12
Classifier: Programming Language :: Python :: 3.13
Classifier: Topic :: Internet :: WWW/HTTP
Classifier: Topic :: Internet :: WWW/HTTP :: Dynamic Content
Classifier: Topic :: Software Development :: Libraries :: Application Frameworks
Classifier: Topic :: Software Development :: Libraries :: Python Modules
Requires-Python: >=3.11
Requires-Dist: channels>=4.1.0
Requires-Dist: django>=4.1
Requires-Dist: mmh3>=5.1.0
Requires-Dist: orjson>=3.10.7
Requires-Dist: pydantic<3,>=2
Requires-Dist: redis[hiredis]>=5.0.8
Requires-Dist: uuid6>=2024.7.10
Requires-Dist: xotl-tools>=3.1.1
Provides-Extra: logfire
Requires-Dist: logfire[django]>=3.8.0; extra == 'logfire'
Provides-Extra: sentry
Requires-Dist: sentry-sdk>=2.19; extra == 'sentry'
